pyclear/__init__.py
pyclear-1.0.7.dist-info/LICENSE
pyclear-1.0.7.dist-info/METADATA
pyclear-1.0.7.dist-info/WHEEL
pyclear-1.0.7.dist-info/top_level.txt
pyclear-1.0.7.dist-info/RECORD
