Metadata-Version: 2.1
Name: pyclear
Version: 1.0.7
Summary: A simple tool to clear the command line shell you are in
Home-page: https://github.com/PythonEuropa/pyclear
Author: Daniel Smith
Author-email: daniel@waiora.com.au
License: UNKNOWN
Platform: UNKNOWN
Classifier: Programming Language :: Python :: 3
Classifier: License :: OSI Approved :: MIT License
Classifier: Operating System :: OS Independent
Requires-Python: >=3.6
